terminator/__init__.py
terminator/__init__.pyi
terminator/py.typed
terminator/terminator.abi3.so
terminator-0.15.17.dist-info/METADATA
terminator-0.15.17.dist-info/WHEEL
terminator-0.15.17.dist-info/RECORD
